Workbook

Sheet Catalogue LLM
A1: C4RBON GROUP - Catalogue des modeles LLM
A2: Taux USD/EUR | B2: 0.92
A3: Fournisseur | B3: Modele | C3: Input EUR/1M tokens | D3: Output EUR/1M tokens | E3: Contexte | F3: Notes
A4: OpenAI | B4: gpt-5.4 | C4: =2.5*$B$2 -> 2.3 | D4: =15*$B$2 -> 13.8 | E4: 128000
A5: OpenAI | B5: gpt-5.4-pro | C5: =30*$B$2 -> 27.6 | D5: =180*$B$2 -> 165.6 | E5: 128000 | F5: Reasoning
A6: OpenAI | B6: gpt-5.2 | C6: =1.75*$B$2 -> 1.61 | D6: =14*$B$2 -> 12.88 | E6: 128000
A7: OpenAI | B7: gpt-5.1 | C7: =1.25*$B$2 -> 1.15 | D7: =10*$B$2 -> 9.2 | E7: 128000
A8: OpenAI | B8: gpt-5 | C8: =1.25*$B$2 -> 1.15 | D8: =10*$B$2 -> 9.2 | E8: 128000
A9: OpenAI | B9: gpt-5-mini | C9: =0.25*$B$2 -> 0.23 | D9: =2*$B$2 -> 1.84 | E9: 128000 | F9: Recommande
A10: OpenAI | B10: gpt-5-nano | C10: =0.05*$B$2 -> 0.046 | D10: =0.4*$B$2 -> 0.368 | E10: 128000 | F10: Ultra-leger
A11: OpenAI | B11: gpt-4.1 | C11: =2*$B$2 -> 1.84 | D11: =8*$B$2 -> 7.36 | E11: 1048576 | F11: 1M contexte
A12: OpenAI | B12: gpt-4.1-mini | C12: =0.4*$B$2 -> 0.368 | D12: =1.6*$B$2 -> 1.472 | E12: 1048576
A13: OpenAI | B13: gpt-4.1-nano | C13: =0.1*$B$2 -> 0.092 | D13: =0.4*$B$2 -> 0.368 | E13: 1048576
A14: OpenAI | B14: o3 | C14: =2*$B$2 -> 1.84 | D14: =8*$B$2 -> 7.36 | E14: 200000 | F14: Reasoning
A15: OpenAI | B15: o3-pro | C15: =20*$B$2 -> 18.4 | D15: =80*$B$2 -> 73.6 | E15: 200000 | F15: Reasoning avance
A16: Anthropic | B16: claude-opus-4.6 | C16: =5*$B$2 -> 4.6 | D16: =25*$B$2 -> 23 | E16: 200000
A17: Anthropic | B17: claude-sonnet-4.6 | C17: =3*$B$2 -> 2.76 | D17: =15*$B$2 -> 13.8 | E17: 200000
A18: Anthropic | B18: claude-haiku-4.5 | C18: =1*$B$2 -> 0.92 | D18: =5*$B$2 -> 4.6 | E18: 200000 | F18: Leger
A19: Anthropic | B19: claude-sonnet-4.5 | C19: =3*$B$2 -> 2.76 | D19: =15*$B$2 -> 13.8 | E19: 200000
A20: Anthropic | B20: claude-opus-4.5 | C20: =5*$B$2 -> 4.6 | D20: =25*$B$2 -> 23 | E20: 200000
A21: Google | B21: gemini-2.5-pro | C21: =2*$B$2 -> 1.84 | D21: =12*$B$2 -> 11.04 | E21: 1048576 | F21: 1M contexte
A22: Google | B22: gemini-2.5-flash | C22: =0.15*$B$2 -> 0.138 | D22: =0.6*$B$2 -> 0.552 | E22: 1048576 | F22: Ultra-leger

Sheet Cout reel IA
A1: C4RBON GROUP - Cout reel des appels IA
A3: A. Parametres modele par defaut
A4: Modele par defaut | B4: gpt-5.2
A5: Input EUR/1M tokens | B5: ='Catalogue LLM'!C6 -> 1.61
A6: Output EUR/1M tokens | B6: ='Catalogue LLM'!D6 -> 12.88
A8: B. Profil utilisation type (par requete)
A9: Tokens input moyens | B9: 2000
A10: Tokens output moyens | B10: 500
A12: C. Cout par requete IA (EUR)
A13: Cout input | B13: =B9/1000000*B5 -> 0.00322
A14: Cout output | B14: =B10/1000000*B6 -> 0.00644
A15: Cout total par requete | B15: =B13+B14 -> 0.00966
A17: D. Volume mensuel par client
A18: Requetes IA / client / mois | B18: 200
A19: Cout IA mensuel / client (EUR) | B19: =B18*B15 -> 1.932
A21: E. Grille par modele
A22: Modele | B22: Input EUR/1M | C22: Output EUR/1M | D22: Cout/requete EUR | E22: Mensuel/client EUR
A23: gpt-5-mini | B23: ='Catalogue LLM'!C9 -> 0.23 | C23: ='Catalogue LLM'!D9 -> 1.84 | D23: =$B$9/1000000*B23+$B$10/1000000*C23 -> 0.00138 | E23: =D23*$B$18 -> 0.276
A24: gpt-5-nano | B24: ='Catalogue LLM'!C10 -> 0.046 | C24: ='Catalogue LLM'!D10 -> 0.368 | D24: =$B$9/1000000*B24+$B$10/1000000*C24 -> 0.000276 | E24: =D24*$B$18 -> 0.0552
A25: gpt-5.2 | B25: ='Catalogue LLM'!C6 -> 1.61 | C25: ='Catalogue LLM'!D6 -> 12.88 | D25: =$B$9/1000000*B25+$B$10/1000000*C25 -> 0.00966 | E25: =D25*$B$18 -> 1.932
A26: gpt-5.4 | B26: ='Catalogue LLM'!C4 -> 2.3 | C26: ='Catalogue LLM'!D4 -> 13.8 | D26: =$B$9/1000000*B26+$B$10/1000000*C26 -> 0.0115 | E26: =D26*$B$18 -> 2.3
A27: claude-sonnet-4.6 | B27: ='Catalogue LLM'!C17 -> 2.76 | C27: ='Catalogue LLM'!D17 -> 13.8 | D27: =$B$9/1000000*B27+$B$10/1000000*C27 -> 0.01242 | E27: =D27*$B$18 -> 2.484
A28: claude-haiku-4.5 | B28: ='Catalogue LLM'!C18 -> 0.92 | C28: ='Catalogue LLM'!D18 -> 4.6 | D28: =$B$9/1000000*B28+$B$10/1000000*C28 -> 0.00414 | E28: =D28*$B$18 -> 0.828
A29: gemini-2.5-flash | B29: ='Catalogue LLM'!C22 -> 0.138 | C29: ='Catalogue LLM'!D22 -> 0.552 | D29: =$B$9/1000000*B29+$B$10/1000000*C29 -> 0.000552 | E29: =D29*$B$18 -> 0.1104

Sheet Execution
A1: C4RBON GROUP - Cout d'execution des workflows
A3: A. Parametres d'execution
A4: Duree moyenne execution (s) | B4: 30
A5: CPU par execution (vCPU) | B5: 0.1
A6: RAM par execution (MiB) | B6: 128
A7: Instance de reference | B7: t4g.medium
A8: Prix instance EUR/h | B8: =0.0336*'Catalogue LLM'!B2 -> 0.030912
A9: vCPU instance | B9: 2
A11: B. Calcul cout par execution (EUR)
A12: Cout instance par seconde | B12: =B8/3600 -> 8.5866667e-06
A13: Part CPU utilisee | B13: =B5/B9 -> 0.05
A14: Cout par execution | B14: =B12*B4*B13 -> 1.288e-05
A16: C. Volume mensuel par client
A17: Exec / client / mois | B17: 500
A18: Cout exec / client / mois (EUR) | B18: =B17*B14 -> 0.00644
A20: D. Grille par volume
A21: Executions/mois | B21: Cout total EUR | C21: Cout/execution EUR
A22: 100 | B22: =A22*$B$14 -> 0.001288 | C22: =$B$14 -> 1.288e-05
A23: 500 | B23: =A23*$B$14 -> 0.00644 | C23: =$B$14 -> 1.288e-05
A24: 1000 | B24: =A24*$B$14 -> 0.01288 | C24: =$B$14 -> 1.288e-05
A25: 2000 | B25: =A25*$B$14 -> 0.02576 | C25: =$B$14 -> 1.288e-05
A26: 5000 | B26: =A26*$B$14 -> 0.0644 | C26: =$B$14 -> 1.288e-05
A27: 10000 | B27: =A27*$B$14 -> 0.1288 | C27: =$B$14 -> 1.288e-05

Sheet Credits Kinn
A1: C4RBON GROUP - Systeme de credits Kinn
A3: A. Definition du credit Kinn
A4: Credits par dollar (ref) | B4: 50
A5: Taux USD/EUR | B5: ='Catalogue LLM'!B2 -> 0.92
A6: Credits par EUR effectif | B6: =B4/B5 -> 54.347826
A7: Cout reel 1 credit (EUR) | B7: =1/B6 -> 0.0184
A9: B. Tarification credits
A10: Marge pay-as-you-go | B10: 3
A11: Marge abonnement | B11: 2
A12: Prix 1 cr pay-as-you-go (EUR) | B12: =B7*B10 -> 0.0552
A13: Prix 1 cr abonnement (EUR) | B13: =B7*B11 -> 0.0368
A15: C. Equivalence credits
A16: Cout 1 requete IA (EUR) | B16: ='Cout reel IA'!B15 -> 0.00966
A17: Credits par requete IA | B17: =B16/B7 -> 0.525
A18: Cout 1 execution (EUR) | B18: =Execution!B14 -> 1.288e-05
A19: Credits par execution | B19: =B18/B7 -> 0.0007
A21: D. Packs pay-as-you-go
A22: Pack | B22: Credits | C22: Prix vente EUR | D22: Cout reel EUR | E22: Marge EUR | F22: Marge %
A23: Decouverte | B23: 500 | C23: =B23*$B$12 -> 27.6 | D23: =B23*$B$7 -> 9.2 | E23: =C23-D23 -> 18.4 | F23: =E23/C23 -> 0.66666667
A24: Standard | B24: 2000 | C24: =B24*$B$12 -> 110.4 | D24: =B24*$B$7 -> 36.8 | E24: =C24-D24 -> 73.6 | F24: =E24/C24 -> 0.66666667
A25: Pro | B25: 5000 | C25: =B25*$B$12 -> 276 | D25: =B25*$B$7 -> 92 | E25: =C25-D25 -> 184 | F25: =E25/C25 -> 0.66666667
A26: Business | B26: 15000 | C26: =B26*$B$12 -> 828 | D26: =B26*$B$7 -> 276 | E26: =C26-D26 -> 552 | F26: =E26/C26 -> 0.66666667
A27: Enterprise | B27: 50000 | C27: =B27*$B$12 -> 2760 | D27: =B27*$B$7 -> 920 | E27: =C27-D27 -> 1840 | F27: =E27/C27 -> 0.66666667

Sheet AWS Infrastructure
A1: C4RBON GROUP - Cout infrastructure AWS K8s
A3: A. Parametres Kubernetes
A4: Overhead CPU K8s (vCPU) | B4: 0.75
A5: Overhead RAM K8s (MiB) | B5: 840
A6: CPU idle par client (vCPU) | B6: 0.3
A7: RAM idle par client (MiB) | B7: 512
A8: Marge CPU securite | B8: 0.2
A9: Marge RAM securite | B9: 0.2
A10: Taux USD/EUR | B10: ='Catalogue LLM'!B2 -> 0.92
A12: B. Couts fixes mensuels (EUR)
A13: Control plane EKS | B13: =73*B10 -> 67.16
A14: ALB | B14: =25*B10 -> 23
A15: NAT Gateway | B15: =35*B10 -> 32.2
A16: EBS stockage | B16: =25*B10 -> 23
A17: Monitoring | B17: =15*B10 -> 13.8
A18: Total fixe EUR/mois | B18: =SUM(B13:B17) -> 159.16
A20: C. Scaling par nombre de clients
A21: Clients | B21: Instance | C21: vCPU | D21: RAM GiB | E21: Prix EUR/h | F21: Workers | G21: Cout workers EUR/mois | H21: Cout fixe EUR/mois | I21: Cout total EUR/mois | J21: Cout/client EUR/mois | K21: CPU util. % | L21: RAM util. %
A22: 5 | B22: t4g.small | C22: 2 | D22: 2 | E22: =0.0168*$B$10 -> 0.015456 | F22: =CEILING(A22*$B$6*(1+$B$8)/(C22-$B$4),1) -> 2 | G22: =F22*E22*730 -> 22.56576 | H22: =$B$18 -> 159.16 | I22: =G22+H22 -> 181.72576 | J22: =I22/A22 -> 36.345152 | K22: =A22*$B$6/(F22*(C22-$B$4)) -> 0.6 | L22: =A22*$B$7/(F22*(D22*1024-$B$5)) -> 1.0596026
A23: 10 | B23: t4g.small | C23: 2 | D23: 2 | E23: =0.0168*$B$10 -> 0.015456 | F23: =CEILING(A23*$B$6*(1+$B$8)/(C23-$B$4),1) -> 3 | G23: =F23*E23*730 -> 33.84864 | H23: =$B$18 -> 159.16 | I23: =G23+H23 -> 193.00864 | J23: =I23/A23 -> 19.300864 | K23: =A23*$B$6/(F23*(C23-$B$4)) -> 0.8 | L23: =A23*$B$7/(F23*(D23*1024-$B$5)) -> 1.4128035
A24: 20 | B24: t4g.medium | C24: 2 | D24: 4 | E24: =0.0336*$B$10 -> 0.030912 | F24: =CEILING(A24*$B$6*(1+$B$8)/(C24-$B$4),1) -> 6 | G24: =F24*E24*730 -> 135.39456 | H24: =$B$18 -> 159.16 | I24: =G24+H24 -> 294.55456 | J24: =I24/A24 -> 14.727728 | K24: =A24*$B$6/(F24*(C24-$B$4)) -> 0.8 | L24: =A24*$B$7/(F24*(D24*1024-$B$5)) -> 0.52416052
A25: 30 | B25: t4g.medium | C25: 2 | D25: 4 | E25: =0.0336*$B$10 -> 0.030912 | F25: =CEILING(A25*$B$6*(1+$B$8)/(C25-$B$4),1) -> 9 | G25: =F25*E25*730 -> 203.09184 | H25: =$B$18 -> 159.16 | I25: =G25+H25 -> 362.25184 | J25: =I25/A25 -> 12.075061 | K25: =A25*$B$6/(F25*(C25-$B$4)) -> 0.8 | L25: =A25*$B$7/(F25*(D25*1024-$B$5)) -> 0.52416052
A26: 50 | B26: t4g.medium | C26: 2 | D26: 4 | E26: =0.0336*$B$10 -> 0.030912 | F26: =CEILING(A26*$B$6*(1+$B$8)/(C26-$B$4),1) -> 15 | G26: =F26*E26*730 -> 338.4864 | H26: =$B$18 -> 159.16 | I26: =G26+H26 -> 497.6464 | J26: =I26/A26 -> 9.952928 | K26: =A26*$B$6/(F26*(C26-$B$4)) -> 0.8 | L26: =A26*$B$7/(F26*(D26*1024-$B$5)) -> 0.52416052
A27: 75 | B27: t4g.large | C27: 2 | D27: 8 | E27: =0.0672*$B$10 -> 0.061824 | F27: =CEILING(A27*$B$6*(1+$B$8)/(C27-$B$4),1) -> 22 | G27: =F27*E27*730 -> 992.89344 | H27: =$B$18 -> 159.16 | I27: =G27+H27 -> 1152.0534 | J27: =I27/A27 -> 15.360713 | K27: =A27*$B$6/(F27*(C27-$B$4)) -> 0.81818182 | L27: =A27*$B$7/(F27*(D27*1024-$B$5)) -> 0.23741221
A28: 100 | B28: t4g.large | C28: 2 | D28: 8 | E28: =0.0672*$B$10 -> 0.061824 | F28: =CEILING(A28*$B$6*(1+$B$8)/(C28-$B$4),1) -> 29 | G28: =F28*E28*730 -> 1308.8141 | H28: =$B$18 -> 159.16 | I28: =G28+H28 -> 1467.9741 | J28: =I28/A28 -> 14.679741 | K28: =A28*$B$6/(F28*(C28-$B$4)) -> 0.82758621 | L28: =A28*$B$7/(F28*(D28*1024-$B$5)) -> 0.24014108
A29: 150 | B29: t4g.xlarge | C29: 4 | D29: 16 | E29: =0.1344*$B$10 -> 0.123648 | F29: =CEILING(A29*$B$6*(1+$B$8)/(C29-$B$4),1) -> 17 | G29: =F29*E29*730 -> 1534.4717 | H29: =$B$18 -> 159.16 | I29: =G29+H29 -> 1693.6317 | J29: =I29/A29 -> 11.290878 | K29: =A29*$B$6/(F29*(C29-$B$4)) -> 0.81447964 | L29: =A29*$B$7/(F29*(D29*1024-$B$5)) -> 0.29063607
A30: 200 | B30: t4g.xlarge | C30: 4 | D30: 16 | E30: =0.1344*$B$10 -> 0.123648 | F30: =CEILING(A30*$B$6*(1+$B$8)/(C30-$B$4),1) -> 23 | G30: =F30*E30*730 -> 2076.0499 | H30: =$B$18 -> 159.16 | I30: =G30+H30 -> 2235.2099 | J30: =I30/A30 -> 11.17605 | K30: =A30*$B$6/(F30*(C30-$B$4)) -> 0.80267559 | L30: =A30*$B$7/(F30*(D30*1024-$B$5)) -> 0.28642395
A31: 300 | B31: m7g.xlarge | C31: 4 | D31: 16 | E31: =0.1632*$B$10 -> 0.150144 | F31: =CEILING(A31*$B$6*(1+$B$8)/(C31-$B$4),1) -> 34 | G31: =F31*E31*730 -> 3726.5741 | H31: =$B$18 -> 159.16 | I31: =G31+H31 -> 3885.7341 | J31: =I31/A31 -> 12.952447 | K31: =A31*$B$6/(F31*(C31-$B$4)) -> 0.81447964 | L31: =A31*$B$7/(F31*(D31*1024-$B$5)) -> 0.29063607
A32: 500 | B32: m7g.xlarge | C32: 4 | D32: 16 | E32: =0.1632*$B$10 -> 0.150144 | F32: =CEILING(A32*$B$6*(1+$B$8)/(C32-$B$4),1) -> 56 | G32: =F32*E32*730 -> 6137.8867 | H32: =$B$18 -> 159.16 | I32: =G32+H32 -> 6297.0467 | J32: =I32/A32 -> 12.594093 | K32: =A32*$B$6/(F32*(C32-$B$4)) -> 0.82417582 | L32: =A32*$B$7/(F32*(D32*1024-$B$5)) -> 0.29409602
A33: 750 | B33: m7g.2xlarge | C33: 8 | D33: 32 | E33: =0.3264*$B$10 -> 0.300288 | F33: =CEILING(A33*$B$6*(1+$B$8)/(C33-$B$4),1) -> 38 | G33: =F33*E33*730 -> 8329.9891 | H33: =$B$18 -> 159.16 | I33: =G33+H33 -> 8489.1491 | J33: =I33/A33 -> 11.318865 | K33: =A33*$B$6/(F33*(C33-$B$4)) -> 0.81669691 | L33: =A33*$B$7/(F33*(D33*1024-$B$5)) -> 0.3165016
A34: 1000 | B34: m7g.2xlarge | C34: 8 | D34: 32 | E34: =0.3264*$B$10 -> 0.300288 | F34: =CEILING(A34*$B$6*(1+$B$8)/(C34-$B$4),1) -> 50 | G34: =F34*E34*730 -> 10960.512 | H34: =$B$18 -> 159.16 | I34: =G34+H34 -> 11119.672 | J34: =I34/A34 -> 11.119672 | K34: =A34*$B$6/(F34*(C34-$B$4)) -> 0.82758621 | L34: =A34*$B$7/(F34*(D34*1024-$B$5)) -> 0.32072162

Sheet Offres
A1: C4RBON GROUP - Simulateur d'offres Kinn
A2: Remplissez les cellules bleues. Ajoutez une offre dans les colonnes vides.
B4: Starter | C4: Pro | D4: Business | E4: Offre 4 | F4: Offre 5 | G4: Offre 6
A5: PRIX ET INCLUSIONS
A6: Prix mensuel (EUR) | B6: 29 | C6: 79 | D6: 199 | E6: 699
A7: Executions incluses / mois | B7: 1000 | C7: 5000 | D7: 25000 | E7: 100000
A8: Credits IA inclus / mois | B8: 200 | C8: 1000 | D8: 5000 | E8: 25000
A9: Exec supplementaires (au choix) | B9: 0 | C9: 0 | D9: 0
A10: Credits IA supplementaires (au choix) | B10: 0 | C10: 0 | D10: 0
A12: FACTURATION SUPPLEMENT
A13: Prix exec supp. (EUR/exec) | B13: =IF(B6="","",('Credits Kinn'!$B$7*'Credits Kinn'!$B$10*'Credits Kinn'!$B$19)) -> 3.864e-05 | C13: =IF(C6="","",('Credits Kinn'!$B$7*'Credits Kinn'!$B$10*'Credits Kinn'!$B$19)) -> 3.864e-05 | D13: =IF(D6="","",('Credits Kinn'!$B$7*'Credits Kinn'!$B$10*'Credits Kinn'!$B$19)) -> 3.864e-05 | E13: =IF(E6="","",('Credits Kinn'!$B$7*'Credits Kinn'!$B$10*'Credits Kinn'!$B$19)) -> 3.864e-05 | F13: =IF(F6="","",('Credits Kinn'!$B$7*'Credits Kinn'!$B$10*'Credits Kinn'!$B$19)) | G13: =IF(G6="","",('Credits Kinn'!$B$7*'Credits Kinn'!$B$10*'Credits Kinn'!$B$19))
A14: Prix credit supp. pay-as-you-go (EUR/cr) | B14: =IF(B6="","",('Credits Kinn'!$B$12)) -> 0.0552 | C14: =IF(C6="","",('Credits Kinn'!$B$12)) -> 0.0552 | D14: =IF(D6="","",('Credits Kinn'!$B$12)) -> 0.0552 | E14: =IF(E6="","",('Credits Kinn'!$B$12)) -> 0.0552 | F14: =IF(F6="","",('Credits Kinn'!$B$12)) | G14: =IF(G6="","",('Credits Kinn'!$B$12))
A15: Supplement options (EUR/mois) | B15: =IF(B6="","",B9*B13+B10*B14) -> 0 | C15: =IF(C6="","",C9*C13+C10*C14) -> 0 | D15: =IF(D6="","",D9*D13+D10*D14) -> 0 | E15: =IF(E6="","",E9*E13+E10*E14) -> 0 | F15: =IF(F6="","",F9*F13+F10*F14) | G15: =IF(G6="","",G9*G13+G10*G14)
A16: Prix total facture (EUR/mois) | B16: =IF(B6="","",B6+B15) -> 29 | C16: =IF(C6="","",C6+C15) -> 79 | D16: =IF(D6="","",D6+D15) -> 199 | E16: =IF(E6="","",E6+E15) -> 699 | F16: =IF(F6="","",F6+F15) | G16: =IF(G6="","",G6+G15)
A18: COUT REEL PAR CLIENT
A19: Cout executions (incluses + supp.) | B19: =IF(B6="","",(B7+B9)*Execution!$B$14) -> 0.01288 | C19: =IF(C6="","",(C7+C9)*Execution!$B$14) -> 0.0644 | D19: =IF(D6="","",(D7+D9)*Execution!$B$14) -> 0.322 | E19: =IF(E6="","",(E7+E9)*Execution!$B$14) -> 1.288 | F19: =IF(F6="","",(F7+F9)*Execution!$B$14) | G19: =IF(G6="","",(G7+G9)*Execution!$B$14)
A20: Cout credits IA (inclus + supp.) | B20: =IF(B6="","",(B8+B10)*'Credits Kinn'!$B$7) -> 3.68 | C20: =IF(C6="","",(C8+C10)*'Credits Kinn'!$B$7) -> 18.4 | D20: =IF(D6="","",(D8+D10)*'Credits Kinn'!$B$7) -> 92 | E20: =IF(E6="","",(E8+E10)*'Credits Kinn'!$B$7) -> 460 | F20: =IF(F6="","",(F8+F10)*'Credits Kinn'!$B$7) | G20: =IF(G6="","",(G8+G10)*'Credits Kinn'!$B$7)
A21: Cout reel total / client (hors AWS) | B21: =IF(B6="","",B19+B20) -> 3.69288 | C21: =IF(C6="","",C19+C20) -> 18.4644 | D21: =IF(D6="","",D19+D20) -> 92.322 | E21: =IF(E6="","",E19+E20) -> 461.288 | F21: =IF(F6="","",F19+F20) | G21: =IF(G6="","",G19+G20)
A23: MARGE PAR OFFRE
A24: Marge brute EUR (hors AWS) | B24: =IF(B6="","",B16-B21) -> 25.30712 | C24: =IF(C6="","",C16-C21) -> 60.5356 | D24: =IF(D6="","",D16-D21) -> 106.678 | E24: =IF(E6="","",E16-E21) -> 237.712 | F24: =IF(F6="","",F16-F21) | G24: =IF(G6="","",G16-G21)
A25: Marge brute % | B25: =IF(B6="","",B24/B16) -> 0.87265931 | C25: =IF(C6="","",C24/C16) -> 0.76627342 | D25: =IF(D6="","",D24/D16) -> 0.53607035 | E25: =IF(E6="","",E24/E16) -> 0.34007439 | F25: =IF(F6="","",F24/F16) | G25: =IF(G6="","",G24/G16)
A26: Multiplicateur reel (x) | B26: =IF(B6="","",B16/B21) -> 7.8529495 | C26: =IF(C6="","",C16/C21) -> 4.2785035 | D26: =IF(D6="","",D16/D21) -> 2.1554992 | E26: =IF(E6="","",E16/E21) -> 1.5153223 | F26: =IF(F6="","",F16/F21) | G26: =IF(G6="","",G16/G21)
A28: SIMULATION GLOBALE
A29: Nombre de clients total | B29: 100
A31: Repartition clients par offre
B32: =B4 -> Starter | C32: =C4 -> Pro | D32: =D4 -> Business | E32: =E4 -> Offre 4 | F32: =F4 -> Offre 5 | G32: =G4 -> Offre 6
A33: % clients | B33: 0 | C33: 1 | D33: 0 | E33: 0 | F33: 0 | G33: 0
A34: Nombre de clients | B34: =ROUND($B$29*B33,0) -> 0 | C34: =ROUND($B$29*C33,0) -> 100 | D34: =ROUND($B$29*D33,0) -> 0 | E34: =ROUND($B$29*E33,0) -> 0 | F34: =ROUND($B$29*F33,0) -> 0 | G34: =ROUND($B$29*G33,0) -> 0
A35: Controle total % (doit = 100%) | B35: =SUM(B33:G33) -> 1
A37: RESULTATS
A38: Revenu moyen / client (EUR) | B38: =SUMPRODUCT(B33:G33,B16:G16) -> 79
A39: Cout moyen / client hors AWS (EUR) | B39: =SUMPRODUCT(B33:G33,B21:G21) -> 18.4644
A40: Cout AWS total (EUR) | B40: =INDEX('AWS Infrastructure'!I22:I34,MATCH(B29,'AWS Infrastructure'!A22:A34,1)) -> 1467.9741
A41: Cout AWS / client (EUR) | B41: =B40/B29 -> 14.679741
A43: Revenu mensuel total | B43: =B29*B38 -> 7900
A44: Cout total (IA+exec+AWS) | B44: =B29*B39+B40 -> 3314.4141
A45: Marge mensuelle | B45: =B43-B44 -> 4585.5859
A46: Marge % | B46: =B45/B43 -> 0.58045391
A48: Revenu annuel | B48: =B43*12 -> 94800
A49: Marge annuelle | B49: =B45*12 -> 55027.031

Sheet Benchmark Concurrents
A1: C4RBON GROUP - Benchmark concurrents
A3: A. Modeles de facturation
A4: Plateforme | B4: Modele | C4: Unite | D4: Prix indicatif | E4: Inclus gratuit | F4: Notes
A5: n8n Cloud | B5: Par execution | C5: 1 run de workflow complet | D5: 20 EUR (2500 exec) | E5: 2500 exec | F5: Starter: 20 EUR, Pro: 50 EUR
A6: Make.com | B6: Par operation | C6: 1 action dans un scenario | D6: 8,28 EUR (10000 ops) | E6: 1000 ops | F6: Core: 8,28 EUR, Pro: 14,72 EUR
A7: Zapier | B7: Par tache | C7: 1 etape executee dans un zap | D7: 18,40 EUR (750 taches) | E7: 100 taches | F7: Pro: 18,40 EUR, Team: 63,48 EUR
A8: Kinn | B8: Par credit | C8: Unite composite (exec + IA) | D8: Variable selon offre | E8: - | F8: IA incluse dans le credit
A11: B. Comparaison scenario concret
A12: Scenario : 1 client PME - 500 workflows/mois + 200 appels IA
A14: Workflows par mois | B14: 500
A15: Appels IA par mois | B15: 200
A16: Actions par workflow (Make) | B16: 5
A17: Etapes par workflow (Zapier) | B17: 3
A19: Plateforme | B19: Volume facture | C19: Forfait EUR | D19: Cout IA en + EUR | E19: Cout total EUR | F19: IA incluse ?
A20: n8n Cloud | B20: =B14 -> 500 | C20: 50 | D20: =B15*'Cout reel IA'!B15 -> 1.932 | E20: =C20+D20 -> 51.932 | F20: Non
A21: Make.com | B21: =B14*B16 -> 2500 | C21: =9*'Catalogue LLM'!B2 -> 8.28 | D21: =B15*'Cout reel IA'!B15 -> 1.932 | E21: =C21+D21 -> 10.212 | F21: Non
A22: Zapier | B22: =B14*B17 -> 1500 | C22: =20*'Catalogue LLM'!B2 -> 18.4 | D22: =B15*'Cout reel IA'!B15 -> 1.932 | E22: =C22+D22 -> 20.332 | F22: Non
A23: Kinn (offre Pro) | B23: =B14*'Credits Kinn'!B19+B15*'Credits Kinn'!B17 -> 105.35 | C23: =Offres!C26 -> 4.2785035 | D23: 0 | E23: =C23+D23 -> 4.2785035 | F23: Oui

Sheet Projection
A1: C4RBON GROUP - Projection par palier de clients
A3: Parametres lies a la feuille Offres
A4: Rev moyen/client | B4: =Offres!B38 -> 79 | C4: Cout moyen/client (hors AWS) | D4: =Offres!B39 -> 18.4644
A6: Projection par palier
A7: Clients | B7: Revenu EUR | C7: Cout AWS EUR | D7: Cout IA+Exec EUR | E7: Cout total EUR | F7: Marge EUR | G7: Marge % | H7: Rev/client | I7: Cout/client | J7: Exec totales | K7: Req IA totales
A8: 5 | B8: =A8*$B$4 -> 395 | C8: =INDEX('AWS Infrastructure'!I22:I34,MATCH(A8,'AWS Infrastructure'!A22:A34,0)) -> 181.72576 | D8: =A8*$D$4 -> 92.322 | E8: =C8+D8 -> 274.04776 | F8: =B8-E8 -> 120.95224 | G8: =F8/B8 -> 0.3062082 | H8: =B8/A8 -> 79 | I8: =E8/A8 -> 54.809552 | J8: =A8*SUMPRODUCT(Offres!B33:G33,Offres!B7:G7+Offres!B9:G9) -> 25000 | K8: =A8*SUMPRODUCT(Offres!B33:G33,Offres!B8:G8+Offres!B10:G10)/'Credits Kinn'!$B$17 -> 9523.8095
A9: 10 | B9: =A9*$B$4 -> 790 | C9: =INDEX('AWS Infrastructure'!I22:I34,MATCH(A9,'AWS Infrastructure'!A22:A34,0)) -> 193.00864 | D9: =A9*$D$4 -> 184.644 | E9: =C9+D9 -> 377.65264 | F9: =B9-E9 -> 412.34736 | G9: =F9/B9 -> 0.52195868 | H9: =B9/A9 -> 79 | I9: =E9/A9 -> 37.765264 | J9: =A9*SUMPRODUCT(Offres!B33:G33,Offres!B7:G7+Offres!B9:G9) -> 50000 | K9: =A9*SUMPRODUCT(Offres!B33:G33,Offres!B8:G8+Offres!B10:G10)/'Credits Kinn'!$B$17 -> 19047.619
A10: 20 | B10: =A10*$B$4 -> 1580 | C10: =INDEX('AWS Infrastructure'!I22:I34,MATCH(A10,'AWS Infrastructure'!A22:A34,0)) -> 294.55456 | D10: =A10*$D$4 -> 369.288 | E10: =C10+D10 -> 663.84256 | F10: =B10-E10 -> 916.15744 | G10: =F10/B10 -> 0.57984648 | H10: =B10/A10 -> 79 | I10: =E10/A10 -> 33.192128 | J10: =A10*SUMPRODUCT(Offres!B33:G33,Offres!B7:G7+Offres!B9:G9) -> 100000 | K10: =A10*SUMPRODUCT(Offres!B33:G33,Offres!B8:G8+Offres!B10:G10)/'Credits Kinn'!$B$17 -> 38095.238
A11: 30 | B11: =A11*$B$4 -> 2370 | C11: =INDEX('AWS Infrastructure'!I22:I34,MATCH(A11,'AWS Infrastructure'!A22:A34,0)) -> 362.25184 | D11: =A11*$D$4 -> 553.932 | E11: =C11+D11 -> 916.18384 | F11: =B11-E11 -> 1453.8162 | G11: =F11/B11 -> 0.61342454 | H11: =B11/A11 -> 79 | I11: =E11/A11 -> 30.539461 | J11: =A11*SUMPRODUCT(Offres!B33:G33,Offres!B7:G7+Offres!B9:G9) -> 150000 | K11: =A11*SUMPRODUCT(Offres!B33:G33,Offres!B8:G8+Offres!B10:G10)/'Credits Kinn'!$B$17 -> 57142.857
A12: 50 | B12: =A12*$B$4 -> 3950 | C12: =INDEX('AWS Infrastructure'!I22:I34,MATCH(A12,'AWS Infrastructure'!A22:A34,0)) -> 497.6464 | D12: =A12*$D$4 -> 923.22 | E12: =C12+D12 -> 1420.8664 | F12: =B12-E12 -> 2529.1336 | G12: =F12/B12 -> 0.64028699 | H12: =B12/A12 -> 79 | I12: =E12/A12 -> 28.417328 | J12: =A12*SUMPRODUCT(Offres!B33:G33,Offres!B7:G7+Offres!B9:G9) -> 250000 | K12: =A12*SUMPRODUCT(Offres!B33:G33,Offres!B8:G8+Offres!B10:G10)/'Credits Kinn'!$B$17 -> 95238.095
A13: 75 | B13: =A13*$B$4 -> 5925 | C13: =INDEX('AWS Infrastructure'!I22:I34,MATCH(A13,'AWS Infrastructure'!A22:A34,0)) -> 1152.0534 | D13: =A13*$D$4 -> 1384.83 | E13: =C13+D13 -> 2536.8834 | F13: =B13-E13 -> 3388.1166 | G13: =F13/B13 -> 0.57183402 | H13: =B13/A13 -> 79 | I13: =E13/A13 -> 33.825113 | J13: =A13*SUMPRODUCT(Offres!B33:G33,Offres!B7:G7+Offres!B9:G9) -> 375000 | K13: =A13*SUMPRODUCT(Offres!B33:G33,Offres!B8:G8+Offres!B10:G10)/'Credits Kinn'!$B$17 -> 142857.14
A14: 100 | B14: =A14*$B$4 -> 7900 | C14: =INDEX('AWS Infrastructure'!I22:I34,MATCH(A14,'AWS Infrastructure'!A22:A34,0)) -> 1467.9741 | D14: =A14*$D$4 -> 1846.44 | E14: =C14+D14 -> 3314.4141 | F14: =B14-E14 -> 4585.5859 | G14: =F14/B14 -> 0.58045391 | H14: =B14/A14 -> 79 | I14: =E14/A14 -> 33.144141 | J14: =A14*SUMPRODUCT(Offres!B33:G33,Offres!B7:G7+Offres!B9:G9) -> 500000 | K14: =A14*SUMPRODUCT(Offres!B33:G33,Offres!B8:G8+Offres!B10:G10)/'Credits Kinn'!$B$17 -> 190476.19
A15: 150 | B15: =A15*$B$4 -> 11850 | C15: =INDEX('AWS Infrastructure'!I22:I34,MATCH(A15,'AWS Infrastructure'!A22:A34,0)) -> 1693.6317 | D15: =A15*$D$4 -> 2769.66 | E15: =C15+D15 -> 4463.2917 | F15: =B15-E15 -> 7386.7083 | G15: =F15/B15 -> 0.62335091 | H15: =B15/A15 -> 79 | I15: =E15/A15 -> 29.755278 | J15: =A15*SUMPRODUCT(Offres!B33:G33,Offres!B7:G7+Offres!B9:G9) -> 750000 | K15: =A15*SUMPRODUCT(Offres!B33:G33,Offres!B8:G8+Offres!B10:G10)/'Credits Kinn'!$B$17 -> 285714.29
A16: 200 | B16: =A16*$B$4 -> 15800 | C16: =INDEX('AWS Infrastructure'!I22:I34,MATCH(A16,'AWS Infrastructure'!A22:A34,0)) -> 2235.2099 | D16: =A16*$D$4 -> 3692.88 | E16: =C16+D16 -> 5928.0899 | F16: =B16-E16 -> 9871.9101 | G16: =F16/B16 -> 0.62480444 | H16: =B16/A16 -> 79 | I16: =E16/A16 -> 29.64045 | J16: =A16*SUMPRODUCT(Offres!B33:G33,Offres!B7:G7+Offres!B9:G9) -> 1000000 | K16: =A16*SUMPRODUCT(Offres!B33:G33,Offres!B8:G8+Offres!B10:G10)/'Credits Kinn'!$B$17 -> 380952.38
A17: 300 | B17: =A17*$B$4 -> 23700 | C17: =INDEX('AWS Infrastructure'!I22:I34,MATCH(A17,'AWS Infrastructure'!A22:A34,0)) -> 3885.7341 | D17: =A17*$D$4 -> 5539.32 | E17: =C17+D17 -> 9425.0541 | F17: =B17-E17 -> 14274.946 | G17: =F17/B17 -> 0.60231839 | H17: =B17/A17 -> 79 | I17: =E17/A17 -> 31.416847 | J17: =A17*SUMPRODUCT(Offres!B33:G33,Offres!B7:G7+Offres!B9:G9) -> 1500000 | K17: =A17*SUMPRODUCT(Offres!B33:G33,Offres!B8:G8+Offres!B10:G10)/'Credits Kinn'!$B$17 -> 571428.57
A18: 500 | B18: =A18*$B$4 -> 39500 | C18: =INDEX('AWS Infrastructure'!I22:I34,MATCH(A18,'AWS Infrastructure'!A22:A34,0)) -> 6297.0467 | D18: =A18*$D$4 -> 9232.2 | E18: =C18+D18 -> 15529.247 | F18: =B18-E18 -> 23970.753 | G18: =F18/B18 -> 0.60685451 | H18: =B18/A18 -> 79 | I18: =E18/A18 -> 31.058493 | J18: =A18*SUMPRODUCT(Offres!B33:G33,Offres!B7:G7+Offres!B9:G9) -> 2500000 | K18: =A18*SUMPRODUCT(Offres!B33:G33,Offres!B8:G8+Offres!B10:G10)/'Credits Kinn'!$B$17 -> 952380.95
A19: 750 | B19: =A19*$B$4 -> 59250 | C19: =INDEX('AWS Infrastructure'!I22:I34,MATCH(A19,'AWS Infrastructure'!A22:A34,0)) -> 8489.1491 | D19: =A19*$D$4 -> 13848.3 | E19: =C19+D19 -> 22337.449 | F19: =B19-E19 -> 36912.551 | G19: =F19/B19 -> 0.62299664 | H19: =B19/A19 -> 79 | I19: =E19/A19 -> 29.783265 | J19: =A19*SUMPRODUCT(Offres!B33:G33,Offres!B7:G7+Offres!B9:G9) -> 3750000 | K19: =A19*SUMPRODUCT(Offres!B33:G33,Offres!B8:G8+Offres!B10:G10)/'Credits Kinn'!$B$17 -> 1428571.4
A20: 1000 | B20: =A20*$B$4 -> 79000 | C20: =INDEX('AWS Infrastructure'!I22:I34,MATCH(A20,'AWS Infrastructure'!A22:A34,0)) -> 11119.672 | D20: =A20*$D$4 -> 18464.4 | E20: =C20+D20 -> 29584.072 | F20: =B20-E20 -> 49415.928 | G20: =F20/B20 -> 0.62551808 | H20: =B20/A20 -> 79 | I20: =E20/A20 -> 29.584072 | J20: =A20*SUMPRODUCT(Offres!B33:G33,Offres!B7:G7+Offres!B9:G9) -> 5000000 | K20: =A20*SUMPRODUCT(Offres!B33:G33,Offres!B8:G8+Offres!B10:G10)/'Credits Kinn'!$B$17 -> 1904761.9
