Workbook

Sheet Catalogue EC2
A1: C4RBON GROUP - Catalogue EC2 AWS
A3: Instance | B3: Famille | C3: Architecture | D3: vCPU | E3: RAM (GiB) | F3: Prix/h ($) | G3: Prix/mois ($)
A4: t3.micro | B4: T3 | C4: x86_64 | D4: 2 | E4: 1 | F4: 0.0104 | G4: =F4*730 -> 7.592
A5: t3.small | B5: T3 | C5: x86_64 | D5: 2 | E5: 2 | F5: 0.0208 | G5: =F5*730 -> 15.184
A6: t3.medium | B6: T3 | C6: x86_64 | D6: 2 | E6: 4 | F6: 0.0416 | G6: =F6*730 -> 30.368
A7: t3.large | B7: T3 | C7: x86_64 | D7: 2 | E7: 8 | F7: 0.0832 | G7: =F7*730 -> 60.736
A8: t3.xlarge | B8: T3 | C8: x86_64 | D8: 4 | E8: 16 | F8: 0.1664 | G8: =F8*730 -> 121.472
A9: t4g.micro | B9: T4g | C9: ARM64 | D9: 2 | E9: 1 | F9: 0.0084 | G9: =F9*730 -> 6.132
A10: t4g.small | B10: T4g | C10: ARM64 | D10: 2 | E10: 2 | F10: 0.0168 | G10: =F10*730 -> 12.264
A11: t4g.medium | B11: T4g | C11: ARM64 | D11: 2 | E11: 4 | F11: 0.0336 | G11: =F11*730 -> 24.528
A12: t4g.large | B12: T4g | C12: ARM64 | D12: 2 | E12: 8 | F12: 0.0672 | G12: =F12*730 -> 49.056
A13: m6i.large | B13: M6i | C13: x86_64 | D13: 2 | E13: 8 | F13: 0.096 | G13: =F13*730 -> 70.08
A14: m6i.xlarge | B14: M6i | C14: x86_64 | D14: 4 | E14: 16 | F14: 0.192 | G14: =F14*730 -> 140.16
A15: m7g.medium | B15: M7g | C15: ARM64 | D15: 1 | E15: 4 | F15: 0.0408 | G15: =F15*730 -> 29.784
... A17: m7g.xlarge | B17: M7g | C17: ARM64 | D17: 4 | E17: 16 | F17: 0.1632 | G17: =F17*730 -> 119.136

Sheet Parametres
A1: C4RBON GROUP - Parametres du simulateur
A3: A. Application (par client/tenant)
A4: Parametre | B4: Valeur | C4: Unite
A5: CPU idle (vCPU) | B5: 0.3 | C5: vCPU
A6: RAM idle (MB) | B6: 300 | C6: MB
A7: CPU actif (vCPU) | B7: 0.5 | C7: vCPU
A8: RAM actif (MB) | B8: 450 | C8: MB
A9: CPU burst max (vCPU) | B9: 0.8 | C9: vCPU
A10: RAM burst max (MB) | B10: 600 | C10: MB
A11: % clients actifs simultanes | B11: 0.2 | C11: %
A12: Stockage par client (GB EBS) | B12: 5 | C12: GB
A14: B. Overhead K8s + Rancher (par worker node)
A15: Parametre | B15: Valeur | C15: Unite
A16: CPU kubelet | B16: 0.07 | C16: vCPU
A17: CPU system reserved | B17: 0.08 | C17: vCPU
A18: CPU Rancher agent | B18: 0.05 | C18: vCPU
A19: RAM kubelet (MB) | B19: 256 | C19: MB
A20: RAM system reserved (MB) | B20: 200 | C20: MB
A21: RAM Rancher agent (MB) | B21: 256 | C21: MB
A22: CPU kube-proxy + CNI | B22: 0.05 | C22: vCPU
A23: RAM kube-proxy + CNI (MB) | B23: 128 | C23: MB
A24: Marge de securite | B24: 0.1 | C24: %
A26: C. Control Plane
A27: Parametre | B27: Valeur | C27: Unite
A28: Nombre nodes control plane | B28: 3 | C28: nodes
A29: Instance control plane | B29: t3.medium
A30: Prix/h control plane | B30: 0.0416 | C30: $/h
A31: Nombre nodes Rancher server | B31: 1 | C31: nodes
A32: Instance Rancher | B32: t3.medium
A33: Prix/h Rancher | B33: 0.0416 | C33: $/h
A35: D. Couts fixes mensuels
A36: Parametre | B36: Valeur | C36: Unite
A37: EBS gp3 ($/GB/mois) | B37: 0.08 | C37: $/GB/mois
A38: ALB ($/mois) | B38: 22.27 | C38: $/mois
A39: NAT Gateway ($/mois) | B39: 45 | C39: $/mois
A40: Route 53 ($/mois) | B40: 0.5 | C40: $/mois
A41: Data transfer out ($/GB) | B41: 0.09 | C41: $/GB
A42: Transfer estime (GB/client/mois) | B42: 2 | C42: GB/client/mois
A43: ECR ($/mois) | B43: 5 | C43: $/mois
A44: CloudWatch ($/mois) | B44: 10 | C44: $/mois

Sheet Simulateur
A1: C4RBON GROUP - Simulateur AWS K8s Rancher
A3: Configuration
A4: Instance type | B4: t4g.medium
A5: vCPU par worker | B5: 2
A6: RAM par worker (GiB) | B6: 4
A7: Prix/h ($) | B7: 0.0336
A8: Nombre de clients | B8: 30
A9: Heures/mois | B9: 730
A11: Capacite par worker
A13: Overhead CPU/node (vCPU) | B13: =Parametres!B16+Parametres!B17+Parametres!B18+Parametres!B22 -> 0.25
A14: Overhead RAM/node (MB) | B14: =Parametres!B19+Parametres!B20+Parametres!B21+Parametres!B23 -> 840
A16: CPU allocable/worker (vCPU) | B16: =B5-B13 -> 1.75
A17: RAM allocable/worker (MB) | B17: =(B6*1024)-B14 -> 3256
A19: CPU effectif/client (vCPU) | B19: =(Parametres!B7*Parametres!B11)+(Parametres!B5*(1-Parametres!B11)) -> 0.34
A20: RAM effectif/client (MB) | B20: =(Parametres!B8*Parametres!B11)+(Parametres!B6*(1-Parametres!B11)) -> 330
A22: Max clients/worker (CPU) | B22: =FLOOR(B16/B19,1) -> 5
A23: Max clients/worker (RAM) | B23: =FLOOR(B17/B20,1) -> 9
A24: Max clients/worker (final) | B24: =MIN(B22,B23) -> 5
A25: Workers
A26: Workers necessaires | B26: =CEILING(B8/B24,1) -> 6
A27: Workers avec marge (+10%) | B27: =CEILING(B26*(1+Parametres!B24),1) -> 7
A29: Couts mensuels
A30: Workers compute | B30: =B27*B7*B9 -> 171.696
A31: Control Plane | B31: =Parametres!B28*Parametres!B30*B9 -> 91.104
A32: Rancher Server | B32: =Parametres!B31*Parametres!B33*B9 -> 30.368
A33: EBS (clients + workers + CP) | B33: =(B8*Parametres!B37*Parametres!B12)+(B27*50*Parametres!B37)+(Parametres!B28*30*Parametres!B37) -> 47.2
A34: ALB | B34: =Parametres!B38 -> 22.27
A35: NAT Gateway | B35: =Parametres!B39 -> 45
A36: Route 53 | B36: =Parametres!B40 -> 0.5
A37: Data Transfer | B37: =B8*Parametres!B42*Parametres!B41 -> 5.4
A38: ECR | B38: =Parametres!B43 -> 5
A39: CloudWatch | B39: =Parametres!B44 -> 10
A41: TOTAL MENSUEL | B41: =SUM(B30:B39) -> 428.538
A42: Par client/mois | B42: =B41/B8 -> 14.2846
A43: Par client/jour | B43: =B42/30 -> 0.47615333
A44: Utilisation cluster
A45: Utilisation CPU cluster (%) | B45: =(B8*B19)/(B27*B5) -> 0.72857143
A46: Utilisation RAM cluster (%) | B46: =(B8*B20)/(B27*B6*1024) -> 0.3452846

Sheet Scenarios
A1: C4RBON GROUP - Scenarios de deploiement
A3: Metrique | B3: Starter | C3: Small | D3: Medium | E3: Growth | F3: Scale | G3: Enterprise
A4: Instance type | B4: t4g.small | C4: t4g.medium | D4: t4g.medium | E4: t4g.large | F4: m7g.large | G4: m7g.xlarge
A5: vCPU par worker | B5: 2 | C5: 2 | D5: 2 | E5: 2 | F5: 2 | G5: 4
A6: RAM par worker (GiB) | B6: 2 | C6: 4 | D6: 4 | E6: 8 | F6: 8 | G6: 16
A7: Prix/h ($) | B7: 0.0168 | C7: 0.0336 | D7: 0.0336 | E7: 0.0672 | F7: 0.0816 | G7: 0.1632
A8: Nombre de clients | B8: 10 | C8: 25 | D8: 50 | E8: 100 | F8: 200 | G8: 500
A10: Overhead CPU/node (vCPU) | B10: =Parametres!B16+Parametres!B17+Parametres!B18+Parametres!B22 -> 0.25 | C10: =Parametres!B16+Parametres!B17+Parametres!B18+Parametres!B22 -> 0.25 | D10: =Parametres!B16+Parametres!B17+Parametres!B18+Parametres!B22 -> 0.25 | E10: =Parametres!B16+Parametres!B17+Parametres!B18+Parametres!B22 -> 0.25 | F10: =Parametres!B16+Parametres!B17+Parametres!B18+Parametres!B22 -> 0.25 | G10: =Parametres!B16+Parametres!B17+Parametres!B18+Parametres!B22 -> 0.25
A11: Overhead RAM/node (MB) | B11: =Parametres!B19+Parametres!B20+Parametres!B21+Parametres!B23 -> 840 | C11: =Parametres!B19+Parametres!B20+Parametres!B21+Parametres!B23 -> 840 | D11: =Parametres!B19+Parametres!B20+Parametres!B21+Parametres!B23 -> 840 | E11: =Parametres!B19+Parametres!B20+Parametres!B21+Parametres!B23 -> 840 | F11: =Parametres!B19+Parametres!B20+Parametres!B21+Parametres!B23 -> 840 | G11: =Parametres!B19+Parametres!B20+Parametres!B21+Parametres!B23 -> 840
A12: CPU allocable/worker | B12: =B5-B10 -> 1.75 | C12: =C5-C10 -> 1.75 | D12: =D5-D10 -> 1.75 | E12: =E5-E10 -> 1.75 | F12: =F5-F10 -> 1.75 | G12: =G5-G10 -> 3.75
A13: RAM allocable/worker (MB) | B13: =(B6*1024)-B11 -> 1208 | C13: =(C6*1024)-C11 -> 3256 | D13: =(D6*1024)-D11 -> 3256 | E13: =(E6*1024)-E11 -> 7352 | F13: =(F6*1024)-F11 -> 7352 | G13: =(G6*1024)-G11 -> 15544
A14: CPU effectif/client | B14: =(Parametres!B7*Parametres!B11)+(Parametres!B5*(1-Parametres!B11)) -> 0.34 | C14: =(Parametres!B7*Parametres!B11)+(Parametres!B5*(1-Parametres!B11)) -> 0.34 | D14: =(Parametres!B7*Parametres!B11)+(Parametres!B5*(1-Parametres!B11)) -> 0.34 | E14: =(Parametres!B7*Parametres!B11)+(Parametres!B5*(1-Parametres!B11)) -> 0.34 | F14: =(Parametres!B7*Parametres!B11)+(Parametres!B5*(1-Parametres!B11)) -> 0.34 | G14: =(Parametres!B7*Parametres!B11)+(Parametres!B5*(1-Parametres!B11)) -> 0.34
A15: RAM effectif/client (MB) | B15: =(Parametres!B8*Parametres!B11)+(Parametres!B6*(1-Parametres!B11)) -> 330 | C15: =(Parametres!B8*Parametres!B11)+(Parametres!B6*(1-Parametres!B11)) -> 330 | D15: =(Parametres!B8*Parametres!B11)+(Parametres!B6*(1-Parametres!B11)) -> 330 | E15: =(Parametres!B8*Parametres!B11)+(Parametres!B6*(1-Parametres!B11)) -> 330 | F15: =(Parametres!B8*Parametres!B11)+(Parametres!B6*(1-Parametres!B11)) -> 330 | G15: =(Parametres!B8*Parametres!B11)+(Parametres!B6*(1-Parametres!B11)) -> 330
A16: Max clients/worker (CPU) | B16: =FLOOR(B12/B14,1) -> 5 | C16: =FLOOR(C12/C14,1) -> 5 | D16: =FLOOR(D12/D14,1) -> 5 | E16: =FLOOR(E12/E14,1) -> 5 | F16: =FLOOR(F12/F14,1) -> 5 | G16: =FLOOR(G12/G14,1) -> 11
A17: Max clients/worker (RAM) | B17: =FLOOR(B13/B15,1) -> 3 | C17: =FLOOR(C13/C15,1) -> 9 | D17: =FLOOR(D13/D15,1) -> 9 | E17: =FLOOR(E13/E15,1) -> 22 | F17: =FLOOR(F13/F15,1) -> 22 | G17: =FLOOR(G13/G15,1) -> 47
A18: Max clients/worker (final) | B18: =MIN(B16,B17) -> 3 | C18: =MIN(C16,C17) -> 5 | D18: =MIN(D16,D17) -> 5 | E18: =MIN(E16,E17) -> 5 | F18: =MIN(F16,F17) -> 5 | G18: =MIN(G16,G17) -> 11
A19: Workers necessaires | B19: =CEILING(B8/B18,1) -> 4 | C19: =CEILING(C8/C18,1) -> 5 | D19: =CEILING(D8/D18,1) -> 10 | E19: =CEILING(E8/E18,1) -> 20 | F19: =CEILING(F8/F18,1) -> 40 | G19: =CEILING(G8/G18,1) -> 46
A20: Workers avec marge | B20: =CEILING(B19*(1+Parametres!B24),1) -> 5 | C20: =CEILING(C19*(1+Parametres!B24),1) -> 6 | D20: =CEILING(D19*(1+Parametres!B24),1) -> 11 | E20: =CEILING(E19*(1+Parametres!B24),1) -> 22 | F20: =CEILING(F19*(1+Parametres!B24),1) -> 44 | G20: =CEILING(G19*(1+Parametres!B24),1) -> 51
A22: Workers compute ($) | B22: =B20*B7*730 -> 61.32 | C22: =C20*C7*730 -> 147.168 | D22: =D20*D7*730 -> 269.808 | E22: =E20*E7*730 -> 1079.232 | F22: =F20*F7*730 -> 2620.992 | G22: =G20*G7*730 -> 6075.936
A23: Control Plane ($) | B23: =Parametres!B28*Parametres!B30*730 -> 91.104 | C23: =Parametres!B28*Parametres!B30*730 -> 91.104 | D23: =Parametres!B28*Parametres!B30*730 -> 91.104 | E23: =Parametres!B28*Parametres!B30*730 -> 91.104 | F23: =Parametres!B28*Parametres!B30*730 -> 91.104 | G23: =Parametres!B28*Parametres!B30*730 -> 91.104
A24: Rancher Server ($) | B24: =Parametres!B31*Parametres!B33*730 -> 30.368 | C24: =Parametres!B31*Parametres!B33*730 -> 30.368 | D24: =Parametres!B31*Parametres!B33*730 -> 30.368 | E24: =Parametres!B31*Parametres!B33*730 -> 30.368 | F24: =Parametres!B31*Parametres!B33*730 -> 30.368 | G24: =Parametres!B31*Parametres!B33*730 -> 30.368
A25: EBS ($) | B25: =(B8*Parametres!B37*Parametres!B12)+(B20*50*Parametres!B37)+(Parametres!B28*30*Parametres!B37) -> 31.2 | C25: =(C8*Parametres!B37*Parametres!B12)+(C20*50*Parametres!B37)+(Parametres!B28*30*Parametres!B37) -> 41.2 | D25: =(D8*Parametres!B37*Parametres!B12)+(D20*50*Parametres!B37)+(Parametres!B28*30*Parametres!B37) -> 71.2 | E25: =(E8*Parametres!B37*Parametres!B12)+(E20*50*Parametres!B37)+(Parametres!B28*30*Parametres!B37) -> 135.2 | F25: =(F8*Parametres!B37*Parametres!B12)+(F20*50*Parametres!B37)+(Parametres!B28*30*Parametres!B37) -> 263.2 | G25: =(G8*Parametres!B37*Parametres!B12)+(G20*50*Parametres!B37)+(Parametres!B28*30*Parametres!B37) -> 411.2
A26: ALB ($) | B26: =Parametres!B38 -> 22.27 | C26: =Parametres!B38 -> 22.27 | D26: =Parametres!B38 -> 22.27 | E26: =Parametres!B38 -> 22.27 | F26: =Parametres!B38 -> 22.27 | G26: =Parametres!B38 -> 22.27
A27: NAT Gateway ($) | B27: =Parametres!B39 -> 45 | C27: =Parametres!B39 -> 45 | D27: =Parametres!B39 -> 45 | E27: =Parametres!B39 -> 45 | F27: =Parametres!B39 -> 45 | G27: =Parametres!B39 -> 45
A28: Route 53 ($) | B28: =Parametres!B40 -> 0.5 | C28: =Parametres!B40 -> 0.5 | D28: =Parametres!B40 -> 0.5 | E28: =Parametres!B40 -> 0.5 | F28: =Parametres!B40 -> 0.5 | G28: =Parametres!B40 -> 0.5
A29: Data Transfer ($) | B29: =B8*Parametres!B42*Parametres!B41 -> 1.8 | C29: =C8*Parametres!B42*Parametres!B41 -> 4.5 | D29: =D8*Parametres!B42*Parametres!B41 -> 9 | E29: =E8*Parametres!B42*Parametres!B41 -> 18 | F29: =F8*Parametres!B42*Parametres!B41 -> 36 | G29: =G8*Parametres!B42*Parametres!B41 -> 90
A30: ECR ($) | B30: =Parametres!B43 -> 5 | C30: =Parametres!B43 -> 5 | D30: =Parametres!B43 -> 5 | E30: =Parametres!B43 -> 5 | F30: =Parametres!B43 -> 5 | G30: =Parametres!B43 -> 5
A31: CloudWatch ($) | B31: =Parametres!B44 -> 10 | C31: =Parametres!B44 -> 10 | D31: =Parametres!B44 -> 10 | E31: =Parametres!B44 -> 10 | F31: =Parametres!B44 -> 10 | G31: =Parametres!B44 -> 10
A33: TOTAL MENSUEL ($) | B33: =SUM(B22:B31) -> 298.562 | C33: =SUM(C22:C31) -> 397.11 | D33: =SUM(D22:D31) -> 554.25 | E33: =SUM(E22:E31) -> 1436.674 | F33: =SUM(F22:F31) -> 3124.434 | G33: =SUM(G22:G31) -> 6781.378
A34: Par client/mois ($) | B34: =B33/B8 -> 29.8562 | C34: =C33/C8 -> 15.8844 | D34: =D33/D8 -> 11.085 | E34: =E33/E8 -> 14.36674 | F34: =F33/F8 -> 15.62217 | G34: =G33/G8 -> 13.562756
A35: Par client/jour ($) | B35: =B34/30 -> 0.99520667 | C35: =C34/30 -> 0.52948 | D35: =D34/30 -> 0.3695 | E35: =E34/30 -> 0.47889133 | F35: =F34/30 -> 0.520739 | G35: =G34/30 -> 0.45209187
A36: Utilisation CPU (%) | B36: =(B8*B14)/(B20*B5) -> 0.34 | C36: =(C8*C14)/(C20*C5) -> 0.70833333 | D36: =(D8*D14)/(D20*D5) -> 0.77272727 | E36: =(E8*E14)/(E20*E5) -> 0.77272727 | F36: =(F8*F14)/(F20*F5) -> 0.77272727 | G36: =(G8*G14)/(G20*G5) -> 0.83333333
A37: Utilisation RAM (%) | B37: =(B8*B15)/(B20*B6*1024) -> 0.32226562 | C37: =(C8*C15)/(C20*C6*1024) -> 0.33569336 | D37: =(D8*D15)/(D20*D6*1024) -> 0.36621094 | E37: =(E8*E15)/(E20*E6*1024) -> 0.18310547 | F37: =(F8*F15)/(F20*F6*1024) -> 0.18310547 | G37: =(G8*G15)/(G20*G6*1024) -> 0.19746668

Sheet Scaling
A1: C4RBON GROUP - Courbe de scaling
A2: Instance | B2: t4g.medium
A3: vCPU | B3: 2
A4: RAM (GiB) | B4: 4
A5: Prix/h ($) | B5: 0.0336
A7: Clients | B7: OH CPU/node | C7: OH RAM/node (MB) | D7: CPU alloc/worker | E7: RAM alloc/worker (MB) | F7: CPU eff/client | G7: RAM eff/client (MB) | H7: Max cli/w (CPU) | I7: Max cli/w (RAM) | J7: Max cli/w (final) | K7: Workers req. | L7: Workers + marge | M7: Cout workers/mois | N7: Cout CP/mois | O7: Cout Rancher/mois | P7: Cout EBS/mois | Q7: Cout infra fixe/mois | R7: Cout Transfer/mois | S7: TOTAL mensuel | T7: Par client/mois | U7: Par client/jour | V7: Util. CPU (%) | W7: Util. RAM (%)
A8: 5 | B8: =Parametres!B16+Parametres!B17+Parametres!B18+Parametres!B22 -> 0.25 | C8: =Parametres!B19+Parametres!B20+Parametres!B21+Parametres!B23 -> 840 | D8: =$B$3-B8 -> 1.75 | E8: =($B$4*1024)-C8 -> 3256 | F8: =(Parametres!B7*Parametres!B11)+(Parametres!B5*(1-Parametres!B11)) -> 0.34 | G8: =(Parametres!B8*Parametres!B11)+(Parametres!B6*(1-Parametres!B11)) -> 330 | H8: =FLOOR(D8/F8,1) -> 5 | I8: =FLOOR(E8/G8,1) -> 9 | J8: =MIN(H8,I8) -> 5 | K8: =CEILING(A8/J8,1) -> 1 | L8: =CEILING(K8*(1+Parametres!B24),1) -> 2 | M8: =L8*$B$5*730 -> 49.056 | N8: =Parametres!B28*Parametres!B30*730 -> 91.104 | O8: =Parametres!B31*Parametres!B33*730 -> 30.368 | P8: =(A8*Parametres!B37*Parametres!B12)+(L8*50*Parametres!B37)+(Parametres!B28*30*Parametres!B37) -> 17.2 | Q8: =Parametres!B38+Parametres!B39+Parametres!B40+Parametres!B43+Parametres!B44 -> 82.77 | R8: =A8*Parametres!B42*Parametres!B41 -> 0.9 | S8: =SUM(M8:R8) -> 271.398 | T8: =S8/A8 -> 54.2796 | U8: =T8/30 -> 1.80932 | V8: =(A8*F8)/(L8*$B$3) -> 0.425 | W8: =(A8*G8)/(L8*$B$4*1024) -> 0.20141602
A9: 10 | B9: =Parametres!B16+Parametres!B17+Parametres!B18+Parametres!B22 -> 0.25 | C9: =Parametres!B19+Parametres!B20+Parametres!B21+Parametres!B23 -> 840 | D9: =$B$3-B9 -> 1.75 | E9: =($B$4*1024)-C9 -> 3256 | F9: =(Parametres!B7*Parametres!B11)+(Parametres!B5*(1-Parametres!B11)) -> 0.34 | G9: =(Parametres!B8*Parametres!B11)+(Parametres!B6*(1-Parametres!B11)) -> 330 | H9: =FLOOR(D9/F9,1) -> 5 | I9: =FLOOR(E9/G9,1) -> 9 | J9: =MIN(H9,I9) -> 5 | K9: =CEILING(A9/J9,1) -> 2 | L9: =CEILING(K9*(1+Parametres!B24),1) -> 3 | M9: =L9*$B$5*730 -> 73.584 | N9: =Parametres!B28*Parametres!B30*730 -> 91.104 | O9: =Parametres!B31*Parametres!B33*730 -> 30.368 | P9: =(A9*Parametres!B37*Parametres!B12)+(L9*50*Parametres!B37)+(Parametres!B28*30*Parametres!B37) -> 23.2 | Q9: =Parametres!B38+Parametres!B39+Parametres!B40+Parametres!B43+Parametres!B44 -> 82.77 | R9: =A9*Parametres!B42*Parametres!B41 -> 1.8 | S9: =SUM(M9:R9) -> 302.826 | T9: =S9/A9 -> 30.2826 | U9: =T9/30 -> 1.00942 | V9: =(A9*F9)/(L9*$B$3) -> 0.56666667 | W9: =(A9*G9)/(L9*$B$4*1024) -> 0.26855469
A10: 15 | B10: =Parametres!B16+Parametres!B17+Parametres!B18+Parametres!B22 -> 0.25 | C10: =Parametres!B19+Parametres!B20+Parametres!B21+Parametres!B23 -> 840 | D10: =$B$3-B10 -> 1.75 | E10: =($B$4*1024)-C10 -> 3256 | F10: =(Parametres!B7*Parametres!B11)+(Parametres!B5*(1-Parametres!B11)) -> 0.34 | G10: =(Parametres!B8*Parametres!B11)+(Parametres!B6*(1-Parametres!B11)) -> 330 | H10: =FLOOR(D10/F10,1) -> 5 | I10: =FLOOR(E10/G10,1) -> 9 | J10: =MIN(H10,I10) -> 5 | K10: =CEILING(A10/J10,1) -> 3 | L10: =CEILING(K10*(1+Parametres!B24),1) -> 4 | M10: =L10*$B$5*730 -> 98.112 | N10: =Parametres!B28*Parametres!B30*730 -> 91.104 | O10: =Parametres!B31*Parametres!B33*730 -> 30.368 | P10: =(A10*Parametres!B37*Parametres!B12)+(L10*50*Parametres!B37)+(Parametres!B28*30*Parametres!B37) -> 29.2 | Q10: =Parametres!B38+Parametres!B39+Parametres!B40+Parametres!B43+Parametres!B44 -> 82.77 | R10: =A10*Parametres!B42*Parametres!B41 -> 2.7 | S10: =SUM(M10:R10) -> 334.254 | T10: =S10/A10 -> 22.2836 | U10: =T10/30 -> 0.74278667 | V10: =(A10*F10)/(L10*$B$3) -> 0.6375 | W10: =(A10*G10)/(L10*$B$4*1024) -> 0.30212402
A11: 20 | B11: =Parametres!B16+Parametres!B17+Parametres!B18+Parametres!B22 -> 0.25 | C11: =Parametres!B19+Parametres!B20+Parametres!B21+Parametres!B23 -> 840 | D11: =$B$3-B11 -> 1.75 | E11: =($B$4*1024)-C11 -> 3256 | F11: =(Parametres!B7*Parametres!B11)+(Parametres!B5*(1-Parametres!B11)) -> 0.34 | G11: =(Parametres!B8*Parametres!B11)+(Parametres!B6*(1-Parametres!B11)) -> 330 | H11: =FLOOR(D11/F11,1) -> 5 | I11: =FLOOR(E11/G11,1) -> 9 | J11: =MIN(H11,I11) -> 5 | K11: =CEILING(A11/J11,1) -> 4 | L11: =CEILING(K11*(1+Parametres!B24),1) -> 5 | M11: =L11*$B$5*730 -> 122.64 | N11: =Parametres!B28*Parametres!B30*730 -> 91.104 | O11: =Parametres!B31*Parametres!B33*730 -> 30.368 | P11: =(A11*Parametres!B37*Parametres!B12)+(L11*50*Parametres!B37)+(Parametres!B28*30*Parametres!B37) -> 35.2 | Q11: =Parametres!B38+Parametres!B39+Parametres!B40+Parametres!B43+Parametres!B44 -> 82.77 | R11: =A11*Parametres!B42*Parametres!B41 -> 3.6 | S11: =SUM(M11:R11) -> 365.682 | T11: =S11/A11 -> 18.2841 | U11: =T11/30 -> 0.60947 | V11: =(A11*F11)/(L11*$B$3) -> 0.68 | W11: =(A11*G11)/(L11*$B$4*1024) -> 0.32226562
A12: 25 | B12: =Parametres!B16+Parametres!B17+Parametres!B18+Parametres!B22 -> 0.25 | C12: =Parametres!B19+Parametres!B20+Parametres!B21+Parametres!B23 -> 840 | D12: =$B$3-B12 -> 1.75 | E12: =($B$4*1024)-C12 -> 3256 | F12: =(Parametres!B7*Parametres!B11)+(Parametres!B5*(1-Parametres!B11)) -> 0.34 | G12: =(Parametres!B8*Parametres!B11)+(Parametres!B6*(1-Parametres!B11)) -> 330 | H12: =FLOOR(D12/F12,1) -> 5 | I12: =FLOOR(E12/G12,1) -> 9 | J12: =MIN(H12,I12) -> 5 | K12: =CEILING(A12/J12,1) -> 5 | L12: =CEILING(K12*(1+Parametres!B24),1) -> 6 | M12: =L12*$B$5*730 -> 147.168 | N12: =Parametres!B28*Parametres!B30*730 -> 91.104 | O12: =Parametres!B31*Parametres!B33*730 -> 30.368 | P12: =(A12*Parametres!B37*Parametres!B12)+(L12*50*Parametres!B37)+(Parametres!B28*30*Parametres!B37) -> 41.2 | Q12: =Parametres!B38+Parametres!B39+Parametres!B40+Parametres!B43+Parametres!B44 -> 82.77 | R12: =A12*Parametres!B42*Parametres!B41 -> 4.5 | S12: =SUM(M12:R12) -> 397.11 | T12: =S12/A12 -> 15.8844 | U12: =T12/30 -> 0.52948 | V12: =(A12*F12)/(L12*$B$3) -> 0.70833333 | W12: =(A12*G12)/(L12*$B$4*1024) -> 0.33569336
A13: 30 | B13: =Parametres!B16+Parametres!B17+Parametres!B18+Parametres!B22 -> 0.25 | C13: =Parametres!B19+Parametres!B20+Parametres!B21+Parametres!B23 -> 840 | D13: =$B$3-B13 -> 1.75 | E13: =($B$4*1024)-C13 -> 3256 | F13: =(Parametres!B7*Parametres!B11)+(Parametres!B5*(1-Parametres!B11)) -> 0.34 | G13: =(Parametres!B8*Parametres!B11)+(Parametres!B6*(1-Parametres!B11)) -> 330 | H13: =FLOOR(D13/F13,1) -> 5 | I13: =FLOOR(E13/G13,1) -> 9 | J13: =MIN(H13,I13) -> 5 | K13: =CEILING(A13/J13,1) -> 6 | L13: =CEILING(K13*(1+Parametres!B24),1) -> 7 | M13: =L13*$B$5*730 -> 171.696 | N13: =Parametres!B28*Parametres!B30*730 -> 91.104 | O13: =Parametres!B31*Parametres!B33*730 -> 30.368 | P13: =(A13*Parametres!B37*Parametres!B12)+(L13*50*Parametres!B37)+(Parametres!B28*30*Parametres!B37) -> 47.2 | Q13: =Parametres!B38+Parametres!B39+Parametres!B40+Parametres!B43+Parametres!B44 -> 82.77 | R13: =A13*Parametres!B42*Parametres!B41 -> 5.4 | S13: =SUM(M13:R13) -> 428.538 | T13: =S13/A13 -> 14.2846 | U13: =T13/30 -> 0.47615333 | V13: =(A13*F13)/(L13*$B$3) -> 0.72857143 | W13: =(A13*G13)/(L13*$B$4*1024) -> 0.3452846
A14: 40 | B14: =Parametres!B16+Parametres!B17+Parametres!B18+Parametres!B22 -> 0.25 | C14: =Parametres!B19+Parametres!B20+Parametres!B21+Parametres!B23 -> 840 | D14: =$B$3-B14 -> 1.75 | E14: =($B$4*1024)-C14 -> 3256 | F14: =(Parametres!B7*Parametres!B11)+(Parametres!B5*(1-Parametres!B11)) -> 0.34 | G14: =(Parametres!B8*Parametres!B11)+(Parametres!B6*(1-Parametres!B11)) -> 330 | H14: =FLOOR(D14/F14,1) -> 5 | I14: =FLOOR(E14/G14,1) -> 9 | J14: =MIN(H14,I14) -> 5 | K14: =CEILING(A14/J14,1) -> 8 | L14: =CEILING(K14*(1+Parametres!B24),1) -> 9 | M14: =L14*$B$5*730 -> 220.752 | N14: =Parametres!B28*Parametres!B30*730 -> 91.104 | O14: =Parametres!B31*Parametres!B33*730 -> 30.368 | P14: =(A14*Parametres!B37*Parametres!B12)+(L14*50*Parametres!B37)+(Parametres!B28*30*Parametres!B37) -> 59.2 | Q14: =Parametres!B38+Parametres!B39+Parametres!B40+Parametres!B43+Parametres!B44 -> 82.77 | R14: =A14*Parametres!B42*Parametres!B41 -> 7.2 | S14: =SUM(M14:R14) -> 491.394 | T14: =S14/A14 -> 12.28485 | U14: =T14/30 -> 0.409495 | V14: =(A14*F14)/(L14*$B$3) -> 0.75555556 | W14: =(A14*G14)/(L14*$B$4*1024) -> 0.35807292
A15: 50 | B15: =Parametres!B16+Parametres!B17+Parametres!B18+Parametres!B22 -> 0.25 | C15: =Parametres!B19+Parametres!B20+Parametres!B21+Parametres!B23 -> 840 | D15: =$B$3-B15 -> 1.75 | E15: =($B$4*1024)-C15 -> 3256 | F15: =(Parametres!B7*Parametres!B11)+(Parametres!B5*(1-Parametres!B11)) -> 0.34 | G15: =(Parametres!B8*Parametres!B11)+(Parametres!B6*(1-Parametres!B11)) -> 330 | H15: =FLOOR(D15/F15,1) -> 5 | I15: =FLOOR(E15/G15,1) -> 9 | J15: =MIN(H15,I15) -> 5 | K15: =CEILING(A15/J15,1) -> 10 | L15: =CEILING(K15*(1+Parametres!B24),1) -> 11 | M15: =L15*$B$5*730 -> 269.808 | N15: =Parametres!B28*Parametres!B30*730 -> 91.104 | O15: =Parametres!B31*Parametres!B33*730 -> 30.368 | P15: =(A15*Parametres!B37*Parametres!B12)+(L15*50*Parametres!B37)+(Parametres!B28*30*Parametres!B37) -> 71.2 | Q15: =Parametres!B38+Parametres!B39+Parametres!B40+Parametres!B43+Parametres!B44 -> 82.77 | R15: =A15*Parametres!B42*Parametres!B41 -> 9 | S15: =SUM(M15:R15) -> 554.25 | T15: =S15/A15 -> 11.085 | U15: =T15/30 -> 0.3695 | V15: =(A15*F15)/(L15*$B$3) -> 0.77272727 | W15: =(A15*G15)/(L15*$B$4*1024) -> 0.36621094
A16: 75 | B16: =Parametres!B16+Parametres!B17+Parametres!B18+Parametres!B22 -> 0.25 | C16: =Parametres!B19+Parametres!B20+Parametres!B21+Parametres!B23 -> 840 | D16: =$B$3-B16 -> 1.75 | E16: =($B$4*1024)-C16 -> 3256 | F16: =(Parametres!B7*Parametres!B11)+(Parametres!B5*(1-Parametres!B11)) -> 0.34 | G16: =(Parametres!B8*Parametres!B11)+(Parametres!B6*(1-Parametres!B11)) -> 330 | H16: =FLOOR(D16/F16,1) -> 5 | I16: =FLOOR(E16/G16,1) -> 9 | J16: =MIN(H16,I16) -> 5 | K16: =CEILING(A16/J16,1) -> 15 | L16: =CEILING(K16*(1+Parametres!B24),1) -> 17 | M16: =L16*$B$5*730 -> 416.976 | N16: =Parametres!B28*Parametres!B30*730 -> 91.104 | O16: =Parametres!B31*Parametres!B33*730 -> 30.368 | P16: =(A16*Parametres!B37*Parametres!B12)+(L16*50*Parametres!B37)+(Parametres!B28*30*Parametres!B37) -> 105.2 | Q16: =Parametres!B38+Parametres!B39+Parametres!B40+Parametres!B43+Parametres!B44 -> 82.77 | R16: =A16*Parametres!B42*Parametres!B41 -> 13.5 | S16: =SUM(M16:R16) -> 739.918 | T16: =S16/A16 -> 9.8655733 | U16: =T16/30 -> 0.32885244 | V16: =(A16*F16)/(L16*$B$3) -> 0.75 | W16: =(A16*G16)/(L16*$B$4*1024) -> 0.35544003
A17: 100 | B17: =Parametres!B16+Parametres!B17+Parametres!B18+Parametres!B22 -> 0.25 | C17: =Parametres!B19+Parametres!B20+Parametres!B21+Parametres!B23 -> 840 | D17: =$B$3-B17 -> 1.75 | E17: =($B$4*1024)-C17 -> 3256 | F17: =(Parametres!B7*Parametres!B11)+(Parametres!B5*(1-Parametres!B11)) -> 0.34 | G17: =(Parametres!B8*Parametres!B11)+(Parametres!B6*(1-Parametres!B11)) -> 330 | H17: =FLOOR(D17/F17,1) -> 5 | I17: =FLOOR(E17/G17,1) -> 9 | J17: =MIN(H17,I17) -> 5 | K17: =CEILING(A17/J17,1) -> 20 | L17: =CEILING(K17*(1+Parametres!B24),1) -> 22 | M17: =L17*$B$5*730 -> 539.616 | N17: =Parametres!B28*Parametres!B30*730 -> 91.104 | O17: =Parametres!B31*Parametres!B33*730 -> 30.368 | P17: =(A17*Parametres!B37*Parametres!B12)+(L17*50*Parametres!B37)+(Parametres!B28*30*Parametres!B37) -> 135.2 | Q17: =Parametres!B38+Parametres!B39+Parametres!B40+Parametres!B43+Parametres!B44 -> 82.77 | R17: =A17*Parametres!B42*Parametres!B41 -> 18 | S17: =SUM(M17:R17) -> 897.058 | T17: =S17/A17 -> 8.97058 | U17: =T17/30 -> 0.29901933 | V17: =(A17*F17)/(L17*$B$3) -> 0.77272727 | W17: =(A17*G17)/(L17*$B$4*1024) -> 0.36621094
A18: 150 | B18: =Parametres!B16+Parametres!B17+Parametres!B18+Parametres!B22 -> 0.25 | C18: =Parametres!B19+Parametres!B20+Parametres!B21+Parametres!B23 -> 840 | D18: =$B$3-B18 -> 1.75 | E18: =($B$4*1024)-C18 -> 3256 | F18: =(Parametres!B7*Parametres!B11)+(Parametres!B5*(1-Parametres!B11)) -> 0.34 | G18: =(Parametres!B8*Parametres!B11)+(Parametres!B6*(1-Parametres!B11)) -> 330 | H18: =FLOOR(D18/F18,1) -> 5 | I18: =FLOOR(E18/G18,1) -> 9 | J18: =MIN(H18,I18) -> 5 | K18: =CEILING(A18/J18,1) -> 30 | L18: =CEILING(K18*(1+Parametres!B24),1) -> 33 | M18: =L18*$B$5*730 -> 809.424 | N18: =Parametres!B28*Parametres!B30*730 -> 91.104 | O18: =Parametres!B31*Parametres!B33*730 -> 30.368 | P18: =(A18*Parametres!B37*Parametres!B12)+(L18*50*Parametres!B37)+(Parametres!B28*30*Parametres!B37) -> 199.2 | Q18: =Parametres!B38+Parametres!B39+Parametres!B40+Parametres!B43+Parametres!B44 -> 82.77 | R18: =A18*Parametres!B42*Parametres!B41 -> 27 | S18: =SUM(M18:R18) -> 1239.866 | T18: =S18/A18 -> 8.2657733 | U18: =T18/30 -> 0.27552578 | V18: =(A18*F18)/(L18*$B$3) -> 0.77272727 | W18: =(A18*G18)/(L18*$B$4*1024) -> 0.36621094
A19: 200 | B19: =Parametres!B16+Parametres!B17+Parametres!B18+Parametres!B22 -> 0.25 | C19: =Parametres!B19+Parametres!B20+Parametres!B21+Parametres!B23 -> 840 | D19: =$B$3-B19 -> 1.75 | E19: =($B$4*1024)-C19 -> 3256 | F19: =(Parametres!B7*Parametres!B11)+(Parametres!B5*(1-Parametres!B11)) -> 0.34 | G19: =(Parametres!B8*Parametres!B11)+(Parametres!B6*(1-Parametres!B11)) -> 330 | H19: =FLOOR(D19/F19,1) -> 5 | I19: =FLOOR(E19/G19,1) -> 9 | J19: =MIN(H19,I19) -> 5 | K19: =CEILING(A19/J19,1) -> 40 | L19: =CEILING(K19*(1+Parametres!B24),1) -> 44 | M19: =L19*$B$5*730 -> 1079.232 | N19: =Parametres!B28*Parametres!B30*730 -> 91.104 | O19: =Parametres!B31*Parametres!B33*730 -> 30.368 | P19: =(A19*Parametres!B37*Parametres!B12)+(L19*50*Parametres!B37)+(Parametres!B28*30*Parametres!B37) -> 263.2 | Q19: =Parametres!B38+Parametres!B39+Parametres!B40+Parametres!B43+Parametres!B44 -> 82.77 | R19: =A19*Parametres!B42*Parametres!B41 -> 36 | S19: =SUM(M19:R19) -> 1582.674 | T19: =S19/A19 -> 7.91337 | U19: =T19/30 -> 0.263779 | V19: =(A19*F19)/(L19*$B$3) -> 0.77272727 | W19: =(A19*G19)/(L19*$B$4*1024) -> 0.36621094
A20: 300 | B20: =Parametres!B16+Parametres!B17+Parametres!B18+Parametres!B22 -> 0.25 | C20: =Parametres!B19+Parametres!B20+Parametres!B21+Parametres!B23 -> 840 | D20: =$B$3-B20 -> 1.75 | E20: =($B$4*1024)-C20 -> 3256 | F20: =(Parametres!B7*Parametres!B11)+(Parametres!B5*(1-Parametres!B11)) -> 0.34 | G20: =(Parametres!B8*Parametres!B11)+(Parametres!B6*(1-Parametres!B11)) -> 330 | H20: =FLOOR(D20/F20,1) -> 5 | I20: =FLOOR(E20/G20,1) -> 9 | J20: =MIN(H20,I20) -> 5 | K20: =CEILING(A20/J20,1) -> 60 | L20: =CEILING(K20*(1+Parametres!B24),1) -> 66 | M20: =L20*$B$5*730 -> 1618.848 | N20: =Parametres!B28*Parametres!B30*730 -> 91.104 | O20: =Parametres!B31*Parametres!B33*730 -> 30.368 | P20: =(A20*Parametres!B37*Parametres!B12)+(L20*50*Parametres!B37)+(Parametres!B28*30*Parametres!B37) -> 391.2 | Q20: =Parametres!B38+Parametres!B39+Parametres!B40+Parametres!B43+Parametres!B44 -> 82.77 | R20: =A20*Parametres!B42*Parametres!B41 -> 54 | S20: =SUM(M20:R20) -> 2268.29 | T20: =S20/A20 -> 7.5609667 | U20: =T20/30 -> 0.25203222 | V20: =(A20*F20)/(L20*$B$3) -> 0.77272727 | W20: =(A20*G20)/(L20*$B$4*1024) -> 0.36621094
A21: 400 | B21: =Parametres!B16+Parametres!B17+Parametres!B18+Parametres!B22 -> 0.25 | C21: =Parametres!B19+Parametres!B20+Parametres!B21+Parametres!B23 -> 840 | D21: =$B$3-B21 -> 1.75 | E21: =($B$4*1024)-C21 -> 3256 | F21: =(Parametres!B7*Parametres!B11)+(Parametres!B5*(1-Parametres!B11)) -> 0.34 | G21: =(Parametres!B8*Parametres!B11)+(Parametres!B6*(1-Parametres!B11)) -> 330 | H21: =FLOOR(D21/F21,1) -> 5 | I21: =FLOOR(E21/G21,1) -> 9 | J21: =MIN(H21,I21) -> 5 | K21: =CEILING(A21/J21,1) -> 80 | L21: =CEILING(K21*(1+Parametres!B24),1) -> 88 | M21: =L21*$B$5*730 -> 2158.464 | N21: =Parametres!B28*Parametres!B30*730 -> 91.104 | O21: =Parametres!B31*Parametres!B33*730 -> 30.368 | P21: =(A21*Parametres!B37*Parametres!B12)+(L21*50*Parametres!B37)+(Parametres!B28*30*Parametres!B37) -> 519.2 | Q21: =Parametres!B38+Parametres!B39+Parametres!B40+Parametres!B43+Parametres!B44 -> 82.77 | R21: =A21*Parametres!B42*Parametres!B41 -> 72 | S21: =SUM(M21:R21) -> 2953.906 | T21: =S21/A21 -> 7.384765 | U21: =T21/30 -> 0.24615883 | V21: =(A21*F21)/(L21*$B$3) -> 0.77272727 | W21: =(A21*G21)/(L21*$B$4*1024) -> 0.36621094
A22: 500 | B22: =Parametres!B16+Parametres!B17+Parametres!B18+Parametres!B22 -> 0.25 | C22: =Parametres!B19+Parametres!B20+Parametres!B21+Parametres!B23 -> 840 | D22: =$B$3-B22 -> 1.75 | E22: =($B$4*1024)-C22 -> 3256 | F22: =(Parametres!B7*Parametres!B11)+(Parametres!B5*(1-Parametres!B11)) -> 0.34 | G22: =(Parametres!B8*Parametres!B11)+(Parametres!B6*(1-Parametres!B11)) -> 330 | H22: =FLOOR(D22/F22,1) -> 5 | I22: =FLOOR(E22/G22,1) -> 9 | J22: =MIN(H22,I22) -> 5 | K22: =CEILING(A22/J22,1) -> 100 | L22: =CEILING(K22*(1+Parametres!B24),1) -> 110 | M22: =L22*$B$5*730 -> 2698.08 | N22: =Parametres!B28*Parametres!B30*730 -> 91.104 | O22: =Parametres!B31*Parametres!B33*730 -> 30.368 | P22: =(A22*Parametres!B37*Parametres!B12)+(L22*50*Parametres!B37)+(Parametres!B28*30*Parametres!B37) -> 647.2 | Q22: =Parametres!B38+Parametres!B39+Parametres!B40+Parametres!B43+Parametres!B44 -> 82.77 | R22: =A22*Parametres!B42*Parametres!B41 -> 90 | S22: =SUM(M22:R22) -> 3639.522 | T22: =S22/A22 -> 7.279044 | U22: =T22/30 -> 0.2426348 | V22: =(A22*F22)/(L22*$B$3) -> 0.77272727 | W22: =(A22*G22)/(L22*$B$4*1024) -> 0.36621094
A23: 750 | B23: =Parametres!B16+Parametres!B17+Parametres!B18+Parametres!B22 -> 0.25 | C23: =Parametres!B19+Parametres!B20+Parametres!B21+Parametres!B23 -> 840 | D23: =$B$3-B23 -> 1.75 | E23: =($B$4*1024)-C23 -> 3256 | F23: =(Parametres!B7*Parametres!B11)+(Parametres!B5*(1-Parametres!B11)) -> 0.34 | G23: =(Parametres!B8*Parametres!B11)+(Parametres!B6*(1-Parametres!B11)) -> 330 | H23: =FLOOR(D23/F23,1) -> 5 | I23: =FLOOR(E23/G23,1) -> 9 | J23: =MIN(H23,I23) -> 5 | K23: =CEILING(A23/J23,1) -> 150 | L23: =CEILING(K23*(1+Parametres!B24),1) -> 165 | M23: =L23*$B$5*730 -> 4047.12 | N23: =Parametres!B28*Parametres!B30*730 -> 91.104 | O23: =Parametres!B31*Parametres!B33*730 -> 30.368 | P23: =(A23*Parametres!B37*Parametres!B12)+(L23*50*Parametres!B37)+(Parametres!B28*30*Parametres!B37) -> 967.2 | Q23: =Parametres!B38+Parametres!B39+Parametres!B40+Parametres!B43+Parametres!B44 -> 82.77 | R23: =A23*Parametres!B42*Parametres!B41 -> 135 | S23: =SUM(M23:R23) -> 5353.562 | T23: =S23/A23 -> 7.1380827 | U23: =T23/30 -> 0.23793609 | V23: =(A23*F23)/(L23*$B$3) -> 0.77272727 | W23: =(A23*G23)/(L23*$B$4*1024) -> 0.36621094
A24: 1000 | B24: =Parametres!B16+Parametres!B17+Parametres!B18+Parametres!B22 -> 0.25 | C24: =Parametres!B19+Parametres!B20+Parametres!B21+Parametres!B23 -> 840 | D24: =$B$3-B24 -> 1.75 | E24: =($B$4*1024)-C24 -> 3256 | F24: =(Parametres!B7*Parametres!B11)+(Parametres!B5*(1-Parametres!B11)) -> 0.34 | G24: =(Parametres!B8*Parametres!B11)+(Parametres!B6*(1-Parametres!B11)) -> 330 | H24: =FLOOR(D24/F24,1) -> 5 | I24: =FLOOR(E24/G24,1) -> 9 | J24: =MIN(H24,I24) -> 5 | K24: =CEILING(A24/J24,1) -> 200 | L24: =CEILING(K24*(1+Parametres!B24),1) -> 220 | M24: =L24*$B$5*730 -> 5396.16 | N24: =Parametres!B28*Parametres!B30*730 -> 91.104 | O24: =Parametres!B31*Parametres!B33*730 -> 30.368 | P24: =(A24*Parametres!B37*Parametres!B12)+(L24*50*Parametres!B37)+(Parametres!B28*30*Parametres!B37) -> 1287.2 | Q24: =Parametres!B38+Parametres!B39+Parametres!B40+Parametres!B43+Parametres!B44 -> 82.77 | R24: =A24*Parametres!B42*Parametres!B41 -> 180 | S24: =SUM(M24:R24) -> 7067.602 | T24: =S24/A24 -> 7.067602 | U24: =T24/30 -> 0.23558673 | V24: =(A24*F24)/(L24*$B$3) -> 0.77272727 | W24: =(A24*G24)/(L24*$B$4*1024) -> 0.36621094

Sheet Execution
A1: C4RBON GROUP - Cout et marge par execution
A3: A. Cout d'une execution de workflow
A4: Duree moyenne execution (secondes) | B4: 30
A5: CPU par execution (vCPU) | B5: 0.1
A6: RAM par execution (MB) | B6: 128
A7: Instance worker prix/h ($) | B7: 0.0336
A8: vCPU par worker | B8: 2
A10: Cout CPU par seconde ($) | B10: =B7/(B8*3600) -> 4.6666667e-06
A11: Cout par execution (CPU) ($) | B11: =B10*B5*B4 -> 1.4e-05
A12: Cout stockage/execution (S3, logs) ($) | B12: 0.0001
A13: Cout total par execution ($) | B13: =B11+B12 -> 0.000114
A16: B. Tarification et marge
A19: Prix facture par execution HT ($) | B19: 0.005
A20: Cout par execution ($) | B20: =B13 -> 0.000114
A21: Marge brute par execution ($) | B21: =B19-B20 -> 0.004886
A22: Marge brute (%) | B22: =B21/B19 -> 0.9772
A24: Executions/client/mois (estime) | B24: 1000
A25: Nombre de clients | B25: 50
A26: Executions totales/mois | B26: =B24*B25 -> 50000
A27: Revenu executions/mois ($) | B27: =B26*B19 -> 250
A28: Cout executions/mois ($) | B28: =B26*B20 -> 5.7
A29: Marge executions/mois ($) | B29: =B27-B28 -> 244.3
A32: C. Grille tarifaire executions
A34: Palier | B34: Exec. incluses/mois | C34: Prix forfait/mois ($) | D34: Prix unit. equiv. ($) | E34: Cout reel ($) | F34: Marge ($)
A35: Starter | B35: 500 | C35: 9.9 | D35: =C35/B35 -> 0.0198 | E35: =B35*$B$13 -> 0.057 | F35: =C35-E35 -> 9.843
A36: Pro | B36: 2000 | C36: 29.9 | D36: =C36/B36 -> 0.01495 | E36: =B36*$B$13 -> 0.228 | F36: =C36-E36 -> 29.672
A37: Business | B37: 10000 | C37: 99.9 | D37: =C37/B37 -> 0.00999 | E37: =B37*$B$13 -> 1.14 | F37: =C37-E37 -> 98.76
A38: Enterprise | B38: 50000 | C38: 349.9 | D38: =C38/B38 -> 0.006998 | E38: =B38*$B$13 -> 5.7 | F38: =C38-E38 -> 344.2
A39: Pay-as-you-go | B39: - | C39: - | D39: 0.008 | E39: =$B$13 -> 0.000114 | F39: =D39-E39 -> 0.007886
